[
  {
    "text": "I am brave for living as my authentic self",
    "category": "comingOut"
  },
  {
    "text": "My truth is worth sharing, on my timeline",
    "category": "comingOut"
  },
  {
    "text": "Coming out is a gift I give myself",
    "category": "comingOut"
  },
  {
    "text": "I choose courage over comfort every day",
    "category": "comingOut"
  },
  {
    "text": "My closet door is mine to open when I'm ready",
    "category": "comingOut"
  },
  {
    "text": "Every time I show up as myself, I inspire others",
    "category": "comingOut"
  },
  {
    "text": "I don't owe anyone an explanation for who I am",
    "category": "comingOut"
  },
  {
    "text": "My journey out is valid no matter how long it takes",
    "category": "comingOut"
  },
  {
    "text": "I am not broken for being different",
    "category": "comingOut"
  },
  {
    "text": "The world needs my authentic voice",
    "category": "comingOut"
  },
  {
    "text": "I release the shame that was never mine to carry",
    "category": "comingOut"
  },
  {
    "text": "I trust my own timing",
    "category": "comingOut"
  },
  {
    "text": "Coming out is not a single event \u2014 it's a lifelong act of bravery",
    "category": "comingOut"
  },
  {
    "text": "I am proud of every step I've taken toward my truth",
    "category": "comingOut"
  },
  {
    "text": "My identity is not up for debate",
    "category": "comingOut"
  },
  {
    "text": "I honor the courage it took to acknowledge my truth",
    "category": "comingOut"
  },
  {
    "text": "I deserve to be seen fully and completely",
    "category": "comingOut"
  },
  {
    "text": "My story matters, even the parts I haven't shared yet",
    "category": "comingOut"
  },
  {
    "text": "I am learning that vulnerability is strength",
    "category": "comingOut"
  },
  {
    "text": "Each day I live openly is a victory",
    "category": "comingOut"
  },
  {
    "text": "I choose authenticity over approval",
    "category": "comingOut"
  },
  {
    "text": "I am free to rewrite my own narrative",
    "category": "comingOut"
  },
  {
    "text": "My queerness is not a burden \u2014 it is a superpower",
    "category": "comingOut"
  },
  {
    "text": "I give myself permission to be proud",
    "category": "comingOut"
  },
  {
    "text": "Coming out didn't make me different \u2014 it made me free",
    "category": "comingOut"
  },
  {
    "text": "I celebrate the parts of me I once tried to hide",
    "category": "comingOut"
  },
  {
    "text": "I am exactly who I was meant to be",
    "category": "comingOut"
  },
  {
    "text": "I release the need for everyone's acceptance",
    "category": "comingOut"
  },
  {
    "text": "My bravery ripples out and touches lives I may never know",
    "category": "comingOut"
  },
  {
    "text": "I am allowed to take up space as my full self",
    "category": "comingOut"
  },
  {
    "text": "Living in truth is the greatest act of self-love",
    "category": "comingOut"
  },
  {
    "text": "I refuse to shrink to make others comfortable",
    "category": "comingOut"
  },
  {
    "text": "Every person I come out to is a bridge I build",
    "category": "comingOut"
  },
  {
    "text": "I am worthy of love in every closet and every open sky",
    "category": "comingOut"
  },
  {
    "text": "I didn't lose myself by coming out \u2014 I found myself",
    "category": "comingOut"
  },
  {
    "text": "I am not asking for permission to exist",
    "category": "comingOut"
  },
  {
    "text": "My path to authenticity is sacred",
    "category": "comingOut"
  },
  {
    "text": "I trust that the right people will embrace all of me",
    "category": "comingOut"
  },
  {
    "text": "I am reclaiming the joy that fear once stole from me",
    "category": "comingOut"
  },
  {
    "text": "My honesty is a gift to myself and the world",
    "category": "comingOut"
  },
  {
    "text": "I am writing a love letter to my younger self with every brave step",
    "category": "comingOut"
  },
  {
    "text": "I am not too much \u2014 I am finally enough",
    "category": "comingOut"
  },
  {
    "text": "I replace fear with faith in who I am",
    "category": "comingOut"
  },
  {
    "text": "I let go of who I was supposed to be and embrace who I am",
    "category": "comingOut"
  },
  {
    "text": "My truth does not need to be palatable to be valid",
    "category": "comingOut"
  },
  {
    "text": "I stand in my identity with quiet confidence",
    "category": "comingOut"
  },
  {
    "text": "I am building a life that reflects my real self",
    "category": "comingOut"
  },
  {
    "text": "I have survived hiding and I will thrive in openness",
    "category": "comingOut"
  },
  {
    "text": "I am not the first and I am not alone",
    "category": "comingOut"
  },
  {
    "text": "I honor every queer person who came out before me and made my path possible",
    "category": "comingOut"
  },
  {
    "text": "I am both the dreamer and the dream come true",
    "category": "comingOut"
  },
  {
    "text": "Today I choose myself",
    "category": "comingOut"
  },
  {
    "text": "I am becoming the person I always knew I was",
    "category": "comingOut"
  },
  {
    "text": "My story is an act of revolution",
    "category": "comingOut"
  },
  {
    "text": "I replace secrecy with self-celebration",
    "category": "comingOut"
  },
  {
    "text": "I am worthy of love exactly as I am",
    "category": "selfAcceptance"
  },
  {
    "text": "My identity is valid and beautiful",
    "category": "selfAcceptance"
  },
  {
    "text": "I embrace every part of who I am without reservation",
    "category": "selfAcceptance"
  },
  {
    "text": "I am not a rough draft \u2014 I am a masterpiece in progress",
    "category": "selfAcceptance"
  },
  {
    "text": "Self-acceptance is not selfish \u2014 it is survival",
    "category": "selfAcceptance"
  },
  {
    "text": "I release the need to be anyone other than myself",
    "category": "selfAcceptance"
  },
  {
    "text": "I am enough, and I have always been enough",
    "category": "selfAcceptance"
  },
  {
    "text": "My worth is not determined by others' understanding of me",
    "category": "selfAcceptance"
  },
  {
    "text": "I give myself the love I once waited for from others",
    "category": "selfAcceptance"
  },
  {
    "text": "I am learning to be gentle with myself",
    "category": "selfAcceptance"
  },
  {
    "text": "I forgive myself for the years I spent at war with who I am",
    "category": "selfAcceptance"
  },
  {
    "text": "My queerness enriches my life in immeasurable ways",
    "category": "selfAcceptance"
  },
  {
    "text": "I deserve tenderness from myself above all",
    "category": "selfAcceptance"
  },
  {
    "text": "Every part of me belongs \u2014 especially the parts I was taught to hide",
    "category": "selfAcceptance"
  },
  {
    "text": "I am whole exactly as I am today",
    "category": "selfAcceptance"
  },
  {
    "text": "I celebrate my identity as a source of strength",
    "category": "selfAcceptance"
  },
  {
    "text": "I don't need to earn my right to exist",
    "category": "selfAcceptance"
  },
  {
    "text": "I am not too queer, too loud, or too much",
    "category": "selfAcceptance"
  },
  {
    "text": "I replace self-doubt with self-compassion",
    "category": "selfAcceptance"
  },
  {
    "text": "My existence is proof that diversity is natural",
    "category": "selfAcceptance"
  },
  {
    "text": "I stop apologizing for who I am",
    "category": "selfAcceptance"
  },
  {
    "text": "I hold space for all of my identities",
    "category": "selfAcceptance"
  },
  {
    "text": "I deserve to love and be loved without conditions",
    "category": "selfAcceptance"
  },
  {
    "text": "I am beautiful in my complexity",
    "category": "selfAcceptance"
  },
  {
    "text": "I am a unique expression of the human experience",
    "category": "selfAcceptance"
  },
  {
    "text": "I accept the parts of me that are still unfolding",
    "category": "selfAcceptance"
  },
  {
    "text": "I choose self-love as a daily practice",
    "category": "selfAcceptance"
  },
  {
    "text": "I trust the wisdom of my own heart",
    "category": "selfAcceptance"
  },
  {
    "text": "I am not confused \u2014 I am clear about who I am",
    "category": "selfAcceptance"
  },
  {
    "text": "I honor my past self for surviving and my present self for thriving",
    "category": "selfAcceptance"
  },
  {
    "text": "My feelings are valid and worthy of attention",
    "category": "selfAcceptance"
  },
  {
    "text": "I give myself credit for how far I've come",
    "category": "selfAcceptance"
  },
  {
    "text": "I am at home in my own skin",
    "category": "selfAcceptance"
  },
  {
    "text": "I release comparison and embrace my own path",
    "category": "selfAcceptance"
  },
  {
    "text": "I have the right to take up space without shrinking",
    "category": "selfAcceptance"
  },
  {
    "text": "I am proud of the person I see in the mirror",
    "category": "selfAcceptance"
  },
  {
    "text": "My identity doesn't need to fit neatly into a box",
    "category": "selfAcceptance"
  },
  {
    "text": "I respect my own boundaries and needs",
    "category": "selfAcceptance"
  },
  {
    "text": "I am not a label \u2014 I am a whole person",
    "category": "selfAcceptance"
  },
  {
    "text": "I am allowed to change, grow, and still be valid",
    "category": "selfAcceptance"
  },
  {
    "text": "I stop seeking permission and start claiming my joy",
    "category": "selfAcceptance"
  },
  {
    "text": "I am a gift to the people who truly see me",
    "category": "selfAcceptance"
  },
  {
    "text": "I let go of perfectionism and welcome wholeness",
    "category": "selfAcceptance"
  },
  {
    "text": "I honor my journey without judging its pace",
    "category": "selfAcceptance"
  },
  {
    "text": "I am more than my worst days",
    "category": "selfAcceptance"
  },
  {
    "text": "I choose to see myself through the eyes of love",
    "category": "selfAcceptance"
  },
  {
    "text": "I am defined by my heart, not by others' opinions",
    "category": "selfAcceptance"
  },
  {
    "text": "I welcome all of my emotions as teachers",
    "category": "selfAcceptance"
  },
  {
    "text": "I am writing a new story where I am the hero",
    "category": "selfAcceptance"
  },
  {
    "text": "I deserve space that celebrates me",
    "category": "selfAcceptance"
  },
  {
    "text": "I trust that self-acceptance opens doors fear never could",
    "category": "selfAcceptance"
  },
  {
    "text": "I choose to be proud of my tender heart",
    "category": "selfAcceptance"
  },
  {
    "text": "My identity is not a phase \u2014 it is who I am",
    "category": "selfAcceptance"
  },
  {
    "text": "I am resilient, radiant, and real",
    "category": "selfAcceptance"
  },
  {
    "text": "I am exactly where I need to be on my journey",
    "category": "selfAcceptance"
  },
  {
    "text": "I am surrounded by people who see and celebrate me",
    "category": "chosenFamily"
  },
  {
    "text": "My chosen family is bound by love, not obligation",
    "category": "chosenFamily"
  },
  {
    "text": "I attract people who honor my full self",
    "category": "chosenFamily"
  },
  {
    "text": "I deserve friendships that feel like home",
    "category": "chosenFamily"
  },
  {
    "text": "My community lifts me up when the world tries to push me down",
    "category": "chosenFamily"
  },
  {
    "text": "I am grateful for the queer elders who paved the way",
    "category": "chosenFamily"
  },
  {
    "text": "I choose to surround myself with people who choose me back",
    "category": "chosenFamily"
  },
  {
    "text": "My found family understands me in ways blood cannot always",
    "category": "chosenFamily"
  },
  {
    "text": "I invest in relationships that nourish my soul",
    "category": "chosenFamily"
  },
  {
    "text": "I am worthy of deep, meaningful connection",
    "category": "chosenFamily"
  },
  {
    "text": "I celebrate the bonds I've built outside of expectation",
    "category": "chosenFamily"
  },
  {
    "text": "My chosen family sees the real me and loves what they see",
    "category": "chosenFamily"
  },
  {
    "text": "I release toxic ties and embrace healing connections",
    "category": "chosenFamily"
  },
  {
    "text": "I am never truly alone \u2014 my community is vast",
    "category": "chosenFamily"
  },
  {
    "text": "I honor the queer friendships that saved my life",
    "category": "chosenFamily"
  },
  {
    "text": "I deserve a seat at tables where I don't have to explain myself",
    "category": "chosenFamily"
  },
  {
    "text": "I build my family with intention and love",
    "category": "chosenFamily"
  },
  {
    "text": "My community is my strength and my shelter",
    "category": "chosenFamily"
  },
  {
    "text": "I give and receive love freely in my chosen family",
    "category": "chosenFamily"
  },
  {
    "text": "I am part of a lineage of queer resilience and joy",
    "category": "chosenFamily"
  },
  {
    "text": "I find belonging in shared experience and mutual care",
    "category": "chosenFamily"
  },
  {
    "text": "I celebrate the diversity within my own community",
    "category": "chosenFamily"
  },
  {
    "text": "I am held by people who understand my journey",
    "category": "chosenFamily"
  },
  {
    "text": "I create safe spaces wherever I go",
    "category": "chosenFamily"
  },
  {
    "text": "My friendships are proof that love is not limited by biology",
    "category": "chosenFamily"
  },
  {
    "text": "I am seen, heard, and valued by the people who matter",
    "category": "chosenFamily"
  },
  {
    "text": "I show up fully for the people who show up for me",
    "category": "chosenFamily"
  },
  {
    "text": "I am part of a beautiful tapestry of chosen connections",
    "category": "chosenFamily"
  },
  {
    "text": "I trust my community to hold me when I can't hold myself",
    "category": "chosenFamily"
  },
  {
    "text": "I honor the courage it takes to build family from scratch",
    "category": "chosenFamily"
  },
  {
    "text": "I am grateful for every queer space that welcomed me",
    "category": "chosenFamily"
  },
  {
    "text": "My found family teaches me new ways to love",
    "category": "chosenFamily"
  },
  {
    "text": "I celebrate the messy, beautiful reality of chosen kinship",
    "category": "chosenFamily"
  },
  {
    "text": "I release the grief of rejection and embrace the gift of belonging",
    "category": "chosenFamily"
  },
  {
    "text": "I am building a legacy of love and acceptance",
    "category": "chosenFamily"
  },
  {
    "text": "I give thanks for the queer mentors who guided me",
    "category": "chosenFamily"
  },
  {
    "text": "I am a safe harbor for others in my community",
    "category": "chosenFamily"
  },
  {
    "text": "My chosen family is my greatest treasure",
    "category": "chosenFamily"
  },
  {
    "text": "I honor the sacred bond between queer siblings",
    "category": "chosenFamily"
  },
  {
    "text": "I am part of something bigger than myself",
    "category": "chosenFamily"
  },
  {
    "text": "I welcome new connections with open arms and an open heart",
    "category": "chosenFamily"
  },
  {
    "text": "I celebrate the people who fought so I could live freely",
    "category": "chosenFamily"
  },
  {
    "text": "I am rooted in a community that celebrates difference",
    "category": "chosenFamily"
  },
  {
    "text": "My people lift me higher than I ever could alone",
    "category": "chosenFamily"
  },
  {
    "text": "I find home in the hearts of those who love me",
    "category": "chosenFamily"
  },
  {
    "text": "I am allowed to grieve what I lost and celebrate what I found",
    "category": "chosenFamily"
  },
  {
    "text": "I honor the spaces \u2014 bars, clubs, centers \u2014 that sheltered us",
    "category": "chosenFamily"
  },
  {
    "text": "I build bridges of understanding within my community",
    "category": "chosenFamily"
  },
  {
    "text": "I am a valued member of a fierce and loving family",
    "category": "chosenFamily"
  },
  {
    "text": "My community's strength flows through me",
    "category": "chosenFamily"
  },
  {
    "text": "I am connected to a proud history of queer solidarity",
    "category": "chosenFamily"
  },
  {
    "text": "I trust that I will always find my people",
    "category": "chosenFamily"
  },
  {
    "text": "I celebrate every act of kindness within my community",
    "category": "chosenFamily"
  },
  {
    "text": "I am home whenever I am with my chosen family",
    "category": "chosenFamily"
  },
  {
    "text": "My love for my community is boundless and fierce",
    "category": "chosenFamily"
  },
  {
    "text": "My existence is an act of pride",
    "category": "queerJoy"
  },
  {
    "text": "I celebrate who I am without apology",
    "category": "queerJoy"
  },
  {
    "text": "Joy is my birthright and I claim it fully",
    "category": "queerJoy"
  },
  {
    "text": "I find delight in the fullness of my identity",
    "category": "queerJoy"
  },
  {
    "text": "My laughter is a revolutionary act",
    "category": "queerJoy"
  },
  {
    "text": "I deserve to feel light, free, and joyful",
    "category": "queerJoy"
  },
  {
    "text": "I am a walking celebration of diversity",
    "category": "queerJoy"
  },
  {
    "text": "Queer joy is resistance and I practice it daily",
    "category": "queerJoy"
  },
  {
    "text": "I allow myself to be silly, playful, and free",
    "category": "queerJoy"
  },
  {
    "text": "I find beauty in the things that make me different",
    "category": "queerJoy"
  },
  {
    "text": "I dance through life on my own terms",
    "category": "queerJoy"
  },
  {
    "text": "My happiness does not depend on anyone's approval",
    "category": "queerJoy"
  },
  {
    "text": "I radiate pride from the inside out",
    "category": "queerJoy"
  },
  {
    "text": "I choose joy as an act of defiance",
    "category": "queerJoy"
  },
  {
    "text": "I am allowed to feel ecstatic about being queer",
    "category": "queerJoy"
  },
  {
    "text": "My life is a celebration that no one can cancel",
    "category": "queerJoy"
  },
  {
    "text": "I find magic in queer spaces and queer faces",
    "category": "queerJoy"
  },
  {
    "text": "I refuse to let the world dim my sparkle",
    "category": "queerJoy"
  },
  {
    "text": "I am proud, loud, and full of joy",
    "category": "queerJoy"
  },
  {
    "text": "Every day I wake up queer is a day worth celebrating",
    "category": "queerJoy"
  },
  {
    "text": "I honor the joy that comes after the struggle",
    "category": "queerJoy"
  },
  {
    "text": "My pride is not seasonal \u2014 it lives in me year-round",
    "category": "queerJoy"
  },
  {
    "text": "I create joy wherever I go",
    "category": "queerJoy"
  },
  {
    "text": "I am grateful for the freedom to love and be loved",
    "category": "queerJoy"
  },
  {
    "text": "I take up space with glitter and grace",
    "category": "queerJoy"
  },
  {
    "text": "I celebrate every queer milestone \u2014 big and small",
    "category": "queerJoy"
  },
  {
    "text": "My joy is contagious and I share it freely",
    "category": "queerJoy"
  },
  {
    "text": "I honor the trailblazers who made my joy possible",
    "category": "queerJoy"
  },
  {
    "text": "I am a rainbow in someone's cloudy sky",
    "category": "queerJoy"
  },
  {
    "text": "I let myself feel the full spectrum of queer happiness",
    "category": "queerJoy"
  },
  {
    "text": "I am the main character in my own love story",
    "category": "queerJoy"
  },
  {
    "text": "I replace shame with celebration",
    "category": "queerJoy"
  },
  {
    "text": "I am proud of every step on my queer journey",
    "category": "queerJoy"
  },
  {
    "text": "I find community in shared laughter and tears",
    "category": "queerJoy"
  },
  {
    "text": "My pride flag flies high in my heart every day",
    "category": "queerJoy"
  },
  {
    "text": "I choose wonder and delight as daily companions",
    "category": "queerJoy"
  },
  {
    "text": "I am electrified by the beauty of queer culture",
    "category": "queerJoy"
  },
  {
    "text": "I live out loud because silence was never meant for me",
    "category": "queerJoy"
  },
  {
    "text": "I celebrate the art, music, and culture born from queer joy",
    "category": "queerJoy"
  },
  {
    "text": "I deserve to thrive, not just survive",
    "category": "queerJoy"
  },
  {
    "text": "I am a living, breathing work of art",
    "category": "queerJoy"
  },
  {
    "text": "My queerness adds color to the world",
    "category": "queerJoy"
  },
  {
    "text": "I find peace in the knowledge that I am exactly right",
    "category": "queerJoy"
  },
  {
    "text": "I am joyful because I am free",
    "category": "queerJoy"
  },
  {
    "text": "I celebrate the courage it takes to love openly",
    "category": "queerJoy"
  },
  {
    "text": "I am a testament to the power of living authentically",
    "category": "queerJoy"
  },
  {
    "text": "My smile is proof that joy wins",
    "category": "queerJoy"
  },
  {
    "text": "I honor the queer joy that sustains us through hard times",
    "category": "queerJoy"
  },
  {
    "text": "I am grateful for every moment of uninhibited happiness",
    "category": "queerJoy"
  },
  {
    "text": "I let go of what others think and hold on to what makes me glow",
    "category": "queerJoy"
  },
  {
    "text": "I am alive with purpose, passion, and pride",
    "category": "queerJoy"
  },
  {
    "text": "I deserve belly laughs, deep love, and wild adventures",
    "category": "queerJoy"
  },
  {
    "text": "My existence makes the world more interesting",
    "category": "queerJoy"
  },
  {
    "text": "I am a firework \u2014 impossible to ignore and beautiful to watch",
    "category": "queerJoy"
  },
  {
    "text": "I celebrate the freedom to be unapologetically me",
    "category": "queerJoy"
  },
  {
    "text": "I am stronger than the hate I face",
    "category": "resilience"
  },
  {
    "text": "My struggles have built an unshakable foundation",
    "category": "resilience"
  },
  {
    "text": "I transform pain into power",
    "category": "resilience"
  },
  {
    "text": "I have survived every difficult day so far",
    "category": "resilience"
  },
  {
    "text": "My resilience is a testament to my spirit",
    "category": "resilience"
  },
  {
    "text": "I rise above every obstacle placed in my path",
    "category": "resilience"
  },
  {
    "text": "I am not defined by what I've endured",
    "category": "resilience"
  },
  {
    "text": "I carry the strength of every queer person who came before me",
    "category": "resilience"
  },
  {
    "text": "I turn my scars into stories of survival",
    "category": "resilience"
  },
  {
    "text": "I am the storm and the calm after it",
    "category": "resilience"
  },
  {
    "text": "I trust my ability to navigate hard times",
    "category": "resilience"
  },
  {
    "text": "I am unbreakable in the face of adversity",
    "category": "resilience"
  },
  {
    "text": "I refuse to be a victim of someone else's ignorance",
    "category": "resilience"
  },
  {
    "text": "My resilience is quiet, powerful, and endless",
    "category": "resilience"
  },
  {
    "text": "I grow through what I go through",
    "category": "resilience"
  },
  {
    "text": "I honor the fight in me that never gave up",
    "category": "resilience"
  },
  {
    "text": "I am still here, and that is everything",
    "category": "resilience"
  },
  {
    "text": "I replace anger with determination",
    "category": "resilience"
  },
  {
    "text": "I am shaped by my struggles but not limited by them",
    "category": "resilience"
  },
  {
    "text": "I channel my pain into progress",
    "category": "resilience"
  },
  {
    "text": "I give myself grace during hard seasons",
    "category": "resilience"
  },
  {
    "text": "I am a survivor and a thriver",
    "category": "resilience"
  },
  {
    "text": "I trust that better days are ahead",
    "category": "resilience"
  },
  {
    "text": "I draw strength from my community's collective resilience",
    "category": "resilience"
  },
  {
    "text": "I am proof that hate cannot win",
    "category": "resilience"
  },
  {
    "text": "I stand tall in the face of discrimination",
    "category": "resilience"
  },
  {
    "text": "I choose healing over hardening",
    "category": "resilience"
  },
  {
    "text": "I am a warrior with a tender heart",
    "category": "resilience"
  },
  {
    "text": "I honor my wounds as evidence of battles won",
    "category": "resilience"
  },
  {
    "text": "I refuse to be erased",
    "category": "resilience"
  },
  {
    "text": "I claim my space in a world that tries to make me small",
    "category": "resilience"
  },
  {
    "text": "I am fueled by the knowledge that I matter",
    "category": "resilience"
  },
  {
    "text": "I meet hatred with dignity and grace",
    "category": "resilience"
  },
  {
    "text": "I am evolving through every challenge",
    "category": "resilience"
  },
  {
    "text": "I protect my peace fiercely",
    "category": "resilience"
  },
  {
    "text": "I am not fragile \u2014 I am forged in fire",
    "category": "resilience"
  },
  {
    "text": "I let go of bitterness and hold on to hope",
    "category": "resilience"
  },
  {
    "text": "I stand on the shoulders of giants who survived before me",
    "category": "resilience"
  },
  {
    "text": "I am brave enough to ask for help when I need it",
    "category": "resilience"
  },
  {
    "text": "I rise, again and again, as many times as it takes",
    "category": "resilience"
  },
  {
    "text": "I am the embodiment of perseverance",
    "category": "resilience"
  },
  {
    "text": "I replace fear with fierce determination",
    "category": "resilience"
  },
  {
    "text": "I honor the cost of being visible",
    "category": "resilience"
  },
  {
    "text": "I am surrounded by a legacy of queer strength",
    "category": "resilience"
  },
  {
    "text": "I deserve rest after the fight",
    "category": "resilience"
  },
  {
    "text": "I am making the world safer for those who come after me",
    "category": "resilience"
  },
  {
    "text": "I hold space for my grief and my growth simultaneously",
    "category": "resilience"
  },
  {
    "text": "I am tough enough to be tender",
    "category": "resilience"
  },
  {
    "text": "I transform every setback into a setup for a comeback",
    "category": "resilience"
  },
  {
    "text": "I am resilient in ways the world will never fully understand",
    "category": "resilience"
  },
  {
    "text": "I choose to keep going because my life has meaning",
    "category": "resilience"
  },
  {
    "text": "I am building a future that honors my past",
    "category": "resilience"
  },
  {
    "text": "I am a phoenix \u2014 reborn from every hardship",
    "category": "resilience"
  },
  {
    "text": "I trust the process of healing, even when it's slow",
    "category": "resilience"
  },
  {
    "text": "I am fierce, I am fabulous, and I am unbreakable",
    "category": "resilience"
  },
  {
    "text": "I deserve a love that honors all of who I am",
    "category": "queerLove"
  },
  {
    "text": "My love is beautiful and valid",
    "category": "queerLove"
  },
  {
    "text": "I am worthy of a partner who celebrates my identity",
    "category": "queerLove"
  },
  {
    "text": "Love is love, and mine is extraordinary",
    "category": "queerLove"
  },
  {
    "text": "I open my heart to love without fear",
    "category": "queerLove"
  },
  {
    "text": "My capacity to love is one of my greatest gifts",
    "category": "queerLove"
  },
  {
    "text": "I deserve romance that makes me feel safe and seen",
    "category": "queerLove"
  },
  {
    "text": "I let go of the idea that queer love is less than",
    "category": "queerLove"
  },
  {
    "text": "My love story is worth telling",
    "category": "queerLove"
  },
  {
    "text": "I attract love that is patient, kind, and affirming",
    "category": "queerLove"
  },
  {
    "text": "I celebrate the many forms love takes in my life",
    "category": "queerLove"
  },
  {
    "text": "I am worthy of passion, tenderness, and devotion",
    "category": "queerLove"
  },
  {
    "text": "My love is not a political statement \u2014 it is a human experience",
    "category": "queerLove"
  },
  {
    "text": "I honor the queer love stories that came before mine",
    "category": "queerLove"
  },
  {
    "text": "I deserve a love that doesn't ask me to hide",
    "category": "queerLove"
  },
  {
    "text": "I am whole on my own and even richer in partnership",
    "category": "queerLove"
  },
  {
    "text": "I trust that the right love will find me",
    "category": "queerLove"
  },
  {
    "text": "I celebrate every queer couple who held hands in public",
    "category": "queerLove"
  },
  {
    "text": "My heart knows what it wants and I trust its wisdom",
    "category": "queerLove"
  },
  {
    "text": "I release shame about who I love",
    "category": "queerLove"
  },
  {
    "text": "I am allowed to want epic, consuming, beautiful love",
    "category": "queerLove"
  },
  {
    "text": "I deserve affection that is freely and proudly given",
    "category": "queerLove"
  },
  {
    "text": "My love expands the definition of what love can be",
    "category": "queerLove"
  },
  {
    "text": "I honor the intimacy of queer connection",
    "category": "queerLove"
  },
  {
    "text": "I am worthy of someone who is proud to be with me",
    "category": "queerLove"
  },
  {
    "text": "I give and receive love with open hands",
    "category": "queerLove"
  },
  {
    "text": "I celebrate the quiet moments of queer domesticity",
    "category": "queerLove"
  },
  {
    "text": "I deserve a love that makes me feel like home",
    "category": "queerLove"
  },
  {
    "text": "I am not settling \u2014 I am waiting for love that matches my worth",
    "category": "queerLove"
  },
  {
    "text": "My love is a revolution and a refuge",
    "category": "queerLove"
  },
  {
    "text": "I trust my heart to guide me toward healthy love",
    "category": "queerLove"
  },
  {
    "text": "I am allowed to redefine what relationships look like for me",
    "category": "queerLove"
  },
  {
    "text": "I honor the bravery it takes to love openly",
    "category": "queerLove"
  },
  {
    "text": "I deserve a partner who holds space for all of me",
    "category": "queerLove"
  },
  {
    "text": "My love is fierce, tender, and world-changing",
    "category": "queerLove"
  },
  {
    "text": "I celebrate the joy of being truly known by another person",
    "category": "queerLove"
  },
  {
    "text": "I am grateful for every love that has shaped me",
    "category": "queerLove"
  },
  {
    "text": "I open myself to deeper intimacy and connection",
    "category": "queerLove"
  },
  {
    "text": "I am worthy of a love that grows and evolves",
    "category": "queerLove"
  },
  {
    "text": "I honor the legacy of queer couples who fought for our rights",
    "category": "queerLove"
  },
  {
    "text": "I deserve a love letter, a slow dance, and a life well-loved",
    "category": "queerLove"
  },
  {
    "text": "My love is a gift to the person I share it with",
    "category": "queerLove"
  },
  {
    "text": "I release old wounds and make room for new love",
    "category": "queerLove"
  },
  {
    "text": "I am deserving of loyalty, respect, and adoration",
    "category": "queerLove"
  },
  {
    "text": "I celebrate the many ways queer people build loving lives",
    "category": "queerLove"
  },
  {
    "text": "I trust that love is abundant and there is enough for me",
    "category": "queerLove"
  },
  {
    "text": "I am allowed to be vulnerable in love",
    "category": "queerLove"
  },
  {
    "text": "My relationship is as valid and sacred as any other",
    "category": "queerLove"
  },
  {
    "text": "I celebrate the small, everyday acts of queer love",
    "category": "queerLove"
  },
  {
    "text": "I am proof that love conquers hate",
    "category": "queerLove"
  },
  {
    "text": "I deserve someone who says my name with love",
    "category": "queerLove"
  },
  {
    "text": "I honor the tenderness between queer partners",
    "category": "queerLove"
  },
  {
    "text": "My love is not defined by heteronormative standards",
    "category": "queerLove"
  },
  {
    "text": "I deserve happiness in love and I am open to receiving it",
    "category": "queerLove"
  },
  {
    "text": "I am a vessel of love, and it overflows",
    "category": "queerLove"
  },
  {
    "text": "My body is my own and it is beautiful",
    "category": "bodyPositivity"
  },
  {
    "text": "I express my gender in ways that feel right",
    "category": "bodyPositivity"
  },
  {
    "text": "I celebrate the body that carries me through life",
    "category": "bodyPositivity"
  },
  {
    "text": "I dress for myself and no one else",
    "category": "bodyPositivity"
  },
  {
    "text": "My body is not an apology",
    "category": "bodyPositivity"
  },
  {
    "text": "I honor my body as a vessel of queer joy",
    "category": "bodyPositivity"
  },
  {
    "text": "I reject beauty standards that don't include me",
    "category": "bodyPositivity"
  },
  {
    "text": "I am at peace with the body I inhabit",
    "category": "bodyPositivity"
  },
  {
    "text": "I choose to see my body through loving eyes",
    "category": "bodyPositivity"
  },
  {
    "text": "My physical form is a canvas for self-expression",
    "category": "bodyPositivity"
  },
  {
    "text": "I release the need to look a certain way to be valid",
    "category": "bodyPositivity"
  },
  {
    "text": "I am beautiful in every expression of my gender",
    "category": "bodyPositivity"
  },
  {
    "text": "My body tells the story of my journey and I am proud of it",
    "category": "bodyPositivity"
  },
  {
    "text": "I nourish my body with love and compassion",
    "category": "bodyPositivity"
  },
  {
    "text": "I celebrate the diversity of queer bodies",
    "category": "bodyPositivity"
  },
  {
    "text": "I am more than my appearance",
    "category": "bodyPositivity"
  },
  {
    "text": "I give myself permission to love my body today \u2014 not someday",
    "category": "bodyPositivity"
  },
  {
    "text": "My body is worthy of pleasure, comfort, and care",
    "category": "bodyPositivity"
  },
  {
    "text": "I dress in ways that make me feel powerful",
    "category": "bodyPositivity"
  },
  {
    "text": "I refuse to apologize for how I present",
    "category": "bodyPositivity"
  },
  {
    "text": "I honor my body's needs without judgment",
    "category": "bodyPositivity"
  },
  {
    "text": "I am beautiful regardless of society's narrow definitions",
    "category": "bodyPositivity"
  },
  {
    "text": "My body is mine to adorn, modify, and celebrate",
    "category": "bodyPositivity"
  },
  {
    "text": "I choose clothes and styles that reflect my inner truth",
    "category": "bodyPositivity"
  },
  {
    "text": "I am learning to love the parts of me I was taught to hide",
    "category": "bodyPositivity"
  },
  {
    "text": "My body deserves gentle, affirming touch",
    "category": "bodyPositivity"
  },
  {
    "text": "I celebrate every scar, stretch mark, and curve",
    "category": "bodyPositivity"
  },
  {
    "text": "I am worthy of feeling good in my own skin",
    "category": "bodyPositivity"
  },
  {
    "text": "I release toxic body comparisons",
    "category": "bodyPositivity"
  },
  {
    "text": "My physical expression is valid and beautiful",
    "category": "bodyPositivity"
  },
  {
    "text": "I honor the relationship between my body and my identity",
    "category": "bodyPositivity"
  },
  {
    "text": "I am allowed to take up physical space unapologetically",
    "category": "bodyPositivity"
  },
  {
    "text": "I celebrate the strength my body gives me",
    "category": "bodyPositivity"
  },
  {
    "text": "My appearance does not determine my worth",
    "category": "bodyPositivity"
  },
  {
    "text": "I am beautiful in stillness and in motion",
    "category": "bodyPositivity"
  },
  {
    "text": "I honor the ways my body has changed and evolved",
    "category": "bodyPositivity"
  },
  {
    "text": "I deserve to feel comfortable and confident",
    "category": "bodyPositivity"
  },
  {
    "text": "My body is an ally in my journey of self-expression",
    "category": "bodyPositivity"
  },
  {
    "text": "I choose to focus on what my body can do, not how it looks",
    "category": "bodyPositivity"
  },
  {
    "text": "I am grateful for a body that lets me experience the world",
    "category": "bodyPositivity"
  },
  {
    "text": "I celebrate the unique ways queer people express beauty",
    "category": "bodyPositivity"
  },
  {
    "text": "I reject shame about my body and embrace self-love",
    "category": "bodyPositivity"
  },
  {
    "text": "My body is not a project \u2014 it is a home",
    "category": "bodyPositivity"
  },
  {
    "text": "I honor my body's signals and respond with care",
    "category": "bodyPositivity"
  },
  {
    "text": "I am allowed to feel beautiful on my own terms",
    "category": "bodyPositivity"
  },
  {
    "text": "I celebrate queer beauty in all its forms",
    "category": "bodyPositivity"
  },
  {
    "text": "My body carries me through life with grace and strength",
    "category": "bodyPositivity"
  },
  {
    "text": "I choose kindness over criticism when I look in the mirror",
    "category": "bodyPositivity"
  },
  {
    "text": "I am proud of the way I present myself to the world",
    "category": "bodyPositivity"
  },
  {
    "text": "I deserve clothing that makes me feel like myself",
    "category": "bodyPositivity"
  },
  {
    "text": "I release society's expectations of how bodies should look",
    "category": "bodyPositivity"
  },
  {
    "text": "I am a work of art \u2014 unique, evolving, and breathtaking",
    "category": "bodyPositivity"
  },
  {
    "text": "I honor the courage it takes to present authentically",
    "category": "bodyPositivity"
  },
  {
    "text": "My body is beautiful because it is mine",
    "category": "bodyPositivity"
  },
  {
    "text": "I celebrate the freedom to define beauty for myself",
    "category": "bodyPositivity"
  },
  {
    "text": "My pronouns are valid",
    "category": "transNonBinary"
  },
  {
    "text": "I am becoming more myself every day",
    "category": "transNonBinary"
  },
  {
    "text": "My gender identity is real and worthy of respect",
    "category": "transNonBinary"
  },
  {
    "text": "I celebrate the courage of my transition",
    "category": "transNonBinary"
  },
  {
    "text": "I am not between genders \u2014 I am beyond them",
    "category": "transNonBinary"
  },
  {
    "text": "My name is sacred and I deserve to hear it spoken correctly",
    "category": "transNonBinary"
  },
  {
    "text": "I honor the person I am becoming",
    "category": "transNonBinary"
  },
  {
    "text": "I am valid whether I pass or not",
    "category": "transNonBinary"
  },
  {
    "text": "My gender is my own to define",
    "category": "transNonBinary"
  },
  {
    "text": "I celebrate every step of my journey \u2014 medical or not",
    "category": "transNonBinary"
  },
  {
    "text": "I deserve healthcare that affirms my identity",
    "category": "transNonBinary"
  },
  {
    "text": "I am not confused \u2014 I am certain of who I am",
    "category": "transNonBinary"
  },
  {
    "text": "My existence defies limits and that is beautiful",
    "category": "transNonBinary"
  },
  {
    "text": "I honor the fullness of my gender expression",
    "category": "transNonBinary"
  },
  {
    "text": "I am worthy of spaces that welcome all of me",
    "category": "transNonBinary"
  },
  {
    "text": "I celebrate the nonbinary experience as rich and valid",
    "category": "transNonBinary"
  },
  {
    "text": "I trust my body to become my home",
    "category": "transNonBinary"
  },
  {
    "text": "I am not less for being different \u2014 I am more",
    "category": "transNonBinary"
  },
  {
    "text": "I honor the trans people who blazed this trail before me",
    "category": "transNonBinary"
  },
  {
    "text": "I deserve to see myself reflected in the world around me",
    "category": "transNonBinary"
  },
  {
    "text": "My identity is not a costume \u2014 it is my truth",
    "category": "transNonBinary"
  },
  {
    "text": "I am allowed to explore my gender at my own pace",
    "category": "transNonBinary"
  },
  {
    "text": "I celebrate every moment of gender euphoria",
    "category": "transNonBinary"
  },
  {
    "text": "I am more than the gender I was assigned at birth",
    "category": "transNonBinary"
  },
  {
    "text": "I honor my deadname for keeping me safe, and I release it",
    "category": "transNonBinary"
  },
  {
    "text": "I deserve respect in every space I enter",
    "category": "transNonBinary"
  },
  {
    "text": "My transition is a gift I give myself",
    "category": "transNonBinary"
  },
  {
    "text": "I am not a burden for asking to be seen accurately",
    "category": "transNonBinary"
  },
  {
    "text": "I celebrate the beauty of gender diversity",
    "category": "transNonBinary"
  },
  {
    "text": "I am writing a new chapter where I am the author",
    "category": "transNonBinary"
  },
  {
    "text": "I trust my inner knowing about my gender",
    "category": "transNonBinary"
  },
  {
    "text": "I am worthy of love before, during, and after transition",
    "category": "transNonBinary"
  },
  {
    "text": "I celebrate the unique perspective my gender gives me",
    "category": "transNonBinary"
  },
  {
    "text": "I honor the patience my journey requires",
    "category": "transNonBinary"
  },
  {
    "text": "I am not defined by my body alone",
    "category": "transNonBinary"
  },
  {
    "text": "I celebrate the freedom to express my gender fluidly",
    "category": "transNonBinary"
  },
  {
    "text": "I am valid on days when I feel certain and days when I don't",
    "category": "transNonBinary"
  },
  {
    "text": "I deserve mirrors that reflect the real me",
    "category": "transNonBinary"
  },
  {
    "text": "My gender is a spectrum and I exist beautifully on it",
    "category": "transNonBinary"
  },
  {
    "text": "I am allowed to grieve what I lost and celebrate what I've gained",
    "category": "transNonBinary"
  },
  {
    "text": "I honor the silent battles trans people fight daily",
    "category": "transNonBinary"
  },
  {
    "text": "I am more than my medical records",
    "category": "transNonBinary"
  },
  {
    "text": "I celebrate every trans and nonbinary person who lives openly",
    "category": "transNonBinary"
  },
  {
    "text": "I am a pioneer in my own life",
    "category": "transNonBinary"
  },
  {
    "text": "I deserve documentation that matches who I am",
    "category": "transNonBinary"
  },
  {
    "text": "My gender expression is an art form",
    "category": "transNonBinary"
  },
  {
    "text": "I am worth fighting for \u2014 and I fight for myself daily",
    "category": "transNonBinary"
  },
  {
    "text": "I celebrate the small victories of living authentically",
    "category": "transNonBinary"
  },
  {
    "text": "I am not asking for special treatment \u2014 I am asking for basic respect",
    "category": "transNonBinary"
  },
  {
    "text": "I honor the complexity of my identity",
    "category": "transNonBinary"
  },
  {
    "text": "I am whole and complete regardless of where I am in my journey",
    "category": "transNonBinary"
  },
  {
    "text": "I celebrate the joy of finally being seen",
    "category": "transNonBinary"
  },
  {
    "text": "I deserve a world that doesn't question my existence",
    "category": "transNonBinary"
  },
  {
    "text": "My identity is non-negotiable",
    "category": "transNonBinary"
  },
  {
    "text": "I am proud to be trans and I wouldn't have it any other way",
    "category": "transNonBinary"
  },
  {
    "text": "I choose peace today",
    "category": "generalWellness"
  },
  {
    "text": "I am enough, right now, as I am",
    "category": "generalWellness"
  },
  {
    "text": "I deserve rest without guilt",
    "category": "generalWellness"
  },
  {
    "text": "I am kind to myself in moments of struggle",
    "category": "generalWellness"
  },
  {
    "text": "I breathe in calm and breathe out tension",
    "category": "generalWellness"
  },
  {
    "text": "I trust the process of my life",
    "category": "generalWellness"
  },
  {
    "text": "I give myself permission to slow down",
    "category": "generalWellness"
  },
  {
    "text": "I am grounded, centered, and at peace",
    "category": "generalWellness"
  },
  {
    "text": "I welcome this day with an open heart",
    "category": "generalWellness"
  },
  {
    "text": "I honor my need for rest and renewal",
    "category": "generalWellness"
  },
  {
    "text": "I am worthy of joy in the ordinary moments",
    "category": "generalWellness"
  },
  {
    "text": "I choose gratitude as my daily companion",
    "category": "generalWellness"
  },
  {
    "text": "I release what I cannot control",
    "category": "generalWellness"
  },
  {
    "text": "I am present in this moment and it is enough",
    "category": "generalWellness"
  },
  {
    "text": "I trust that I am exactly where I need to be",
    "category": "generalWellness"
  },
  {
    "text": "I give myself grace when I make mistakes",
    "category": "generalWellness"
  },
  {
    "text": "I am learning to love the journey, not just the destination",
    "category": "generalWellness"
  },
  {
    "text": "I deserve health, happiness, and inner peace",
    "category": "generalWellness"
  },
  {
    "text": "I honor my emotions without being consumed by them",
    "category": "generalWellness"
  },
  {
    "text": "I am growing at my own perfect pace",
    "category": "generalWellness"
  },
  {
    "text": "I choose compassion \u2014 for myself and others",
    "category": "generalWellness"
  },
  {
    "text": "I am safe in this moment",
    "category": "generalWellness"
  },
  {
    "text": "I release anxiety and embrace calm",
    "category": "generalWellness"
  },
  {
    "text": "I am worthy of a life that feels good from the inside",
    "category": "generalWellness"
  },
  {
    "text": "I celebrate small wins as building blocks of big change",
    "category": "generalWellness"
  },
  {
    "text": "I give myself permission to feel deeply",
    "category": "generalWellness"
  },
  {
    "text": "I am stronger than my worries",
    "category": "generalWellness"
  },
  {
    "text": "I honor the sacred act of taking care of myself",
    "category": "generalWellness"
  },
  {
    "text": "I deserve days filled with ease and contentment",
    "category": "generalWellness"
  },
  {
    "text": "I am at peace with my past and hopeful for my future",
    "category": "generalWellness"
  },
  {
    "text": "I choose to nourish my mind, body, and spirit",
    "category": "generalWellness"
  },
  {
    "text": "I release perfectionism and welcome progress",
    "category": "generalWellness"
  },
  {
    "text": "I am worthy of deep, restorative sleep",
    "category": "generalWellness"
  },
  {
    "text": "I trust my ability to handle whatever comes",
    "category": "generalWellness"
  },
  {
    "text": "I celebrate the courage it takes to prioritize my well-being",
    "category": "generalWellness"
  },
  {
    "text": "I am gentle with myself on hard days",
    "category": "generalWellness"
  },
  {
    "text": "I deserve to feel calm and centered",
    "category": "generalWellness"
  },
  {
    "text": "I choose to focus on what fills me up",
    "category": "generalWellness"
  },
  {
    "text": "I am enough without doing anything to prove it",
    "category": "generalWellness"
  },
  {
    "text": "I honor the healing power of stillness",
    "category": "generalWellness"
  },
  {
    "text": "I give myself space to breathe and just be",
    "category": "generalWellness"
  },
  {
    "text": "I am worthy of a mind at peace",
    "category": "generalWellness"
  },
  {
    "text": "I release judgment of myself and embrace curiosity",
    "category": "generalWellness"
  },
  {
    "text": "I celebrate every moment of mindfulness",
    "category": "generalWellness"
  },
  {
    "text": "I am building a life rooted in well-being",
    "category": "generalWellness"
  },
  {
    "text": "I trust my body's wisdom about what it needs",
    "category": "generalWellness"
  },
  {
    "text": "I deserve moments of pure, uncomplicated happiness",
    "category": "generalWellness"
  },
  {
    "text": "I am learning that rest is productive",
    "category": "generalWellness"
  },
  {
    "text": "I choose ease over hustle when my spirit needs it",
    "category": "generalWellness"
  },
  {
    "text": "I am allowed to put myself first",
    "category": "generalWellness"
  },
  {
    "text": "I honor the connection between my mental and physical health",
    "category": "generalWellness"
  },
  {
    "text": "I celebrate the courage to ask for support",
    "category": "generalWellness"
  },
  {
    "text": "I am worthy of days that feel nourishing and full",
    "category": "generalWellness"
  },
  {
    "text": "I release the pressure to be perfect and embrace being human",
    "category": "generalWellness"
  },
  {
    "text": "I am grateful for this moment, exactly as it is",
    "category": "generalWellness"
  }
]